pandas_perf_opt/__init__.py
pandas_perf_opt/analyzer.py
pandas_perf_opt/cli.py
pandas_perf_opt/config.py
pandas_perf_opt/reporting.py
pandas_perf_opt/rules.py
pdperf-0.2.0.dist-info/licenses/LICENSE
pdperf-0.2.0.dist-info/METADATA
pdperf-0.2.0.dist-info/WHEEL
pdperf-0.2.0.dist-info/entry_points.txt
pdperf-0.2.0.dist-info/top_level.txt
pdperf-0.2.0.dist-info/RECORD
