Metadata-Version: 2.4
Name: pdperf
Version: 0.2.0
Summary: A static performance linter that detects slow Pandas anti-patterns before they reach production.
Author-email: gadwant <adwantg@gmail.com>
License: MIT
Project-URL: Homepage, https://github.com/adwantg/pdperf
Project-URL: Documentation, https://github.com/adwantg/pdperf#readme
Project-URL: Repository, https://github.com/adwantg/pdperf
Project-URL: Issues, https://github.com/adwantg/pdperf/issues
Project-URL: Changelog, https://github.com/adwantg/pdperf/releases
Keywords: pandas,performance,linter,static-analysis,data-science,optimization,anti-patterns,ci-cd,developer-tools,code-quality
Classifier: Development Status :: 4 - Beta
Classifier: Environment :: Console
Classifier: Intended Audience :: Developers
Classifier: Intended Audience :: Science/Research
Classifier: License :: OSI Approved :: MIT License
Classifier: Operating System :: OS Independent
Classifier: Programming Language :: Python :: 3
Classifier: Programming Language :: Python :: 3.10
Classifier: Programming Language :: Python :: 3.11
Classifier: Programming Language :: Python :: 3.12
Classifier: Programming Language :: Python :: 3.13
Classifier: Topic :: Software Development :: Quality Assurance
Classifier: Topic :: Software Development :: Testing
Classifier: Topic :: Scientific/Engineering
Classifier: Typing :: Typed
Requires-Python: >=3.10
License-File: LICENSE
Provides-Extra: dev
Requires-Dist: pytest>=7.0; extra == "dev"
Requires-Dist: build; extra == "dev"
Requires-Dist: twine; extra == "dev"
Dynamic: license-file
